mongofastlogger.py
mongofastlogger/logger.py
mongofastlogger-0.5.dist-info/LICENSE
mongofastlogger-0.5.dist-info/METADATA
mongofastlogger-0.5.dist-info/WHEEL
mongofastlogger-0.5.dist-info/entry_points.txt
mongofastlogger-0.5.dist-info/top_level.txt
mongofastlogger-0.5.dist-info/RECORD
