Metadata-Version: 2.1
Name: mongofastlogger
Version: 0.5
Summary: A simple and fask logging library that uses the power of mongodb to save and query logs (with built in cli)
Home-page: https://github.com/JakeRoggenbuck/mongofastlogger
Author: Jake Roggenbuck
Author-email: jake@jr0.org
License: MIT
Platform: UNKNOWN
